COPYING
COPYING.lesser
MANIFEST.in
NOTICE
README.md
requirements.txt
setup.py
telectron/__init__.py
telectron/client.py
telectron/dispatcher.py
telectron/emoji.py
telectron/file_id.py
telectron/filters.py
telectron/mime_types.py
telectron/py.typed
telectron/sync.py
telectron/utils.py
telectron.egg-info/PKG-INFO
telectron.egg-info/SOURCES.txt
telectron.egg-info/dependency_links.txt
telectron.egg-info/not-zip-safe
telectron.egg-info/requires.txt
telectron.egg-info/top_level.txt
telectron/connection/__init__.py
telectron/connection/connection.py
telectron/connection/transport/__init__.py
telectron/connection/transport/tcp/__init__.py
telectron/connection/transport/tcp/tcp.py
telectron/connection/transport/tcp/tcp_abridged.py
telectron/connection/transport/tcp/tcp_abridged_o.py
telectron/connection/transport/tcp/tcp_full.py
telectron/connection/transport/tcp/tcp_intermediate.py
telectron/connection/transport/tcp/tcp_intermediate_o.py
telectron/crypto/__init__.py
telectron/crypto/aes.py
telectron/crypto/mtproto.py
telectron/crypto/prime.py
telectron/crypto/rsa.py
telectron/enums/__init__.py
telectron/enums/auto_name.py
telectron/enums/chat_action.py
telectron/enums/chat_event_action.py
telectron/enums/chat_member_status.py
telectron/enums/chat_members_filter.py
telectron/enums/chat_type.py
telectron/enums/message_entity_type.py
telectron/enums/message_media_type.py
telectron/enums/message_service_type.py
telectron/enums/messages_filter.py
telectron/enums/next_code_type.py
telectron/enums/parse_mode.py
telectron/enums/poll_type.py
telectron/enums/sent_code_type.py
telectron/enums/user_status.py
telectron/errors/__init__.py
telectron/errors/rpc_error.py
telectron/errors/exceptions/__init__.py
telectron/errors/exceptions/all.py
telectron/errors/exceptions/bad_request_400.py
telectron/errors/exceptions/flood_420.py
telectron/errors/exceptions/forbidden_403.py
telectron/errors/exceptions/internal_server_error_500.py
telectron/errors/exceptions/not_acceptable_406.py
telectron/errors/exceptions/see_other_303.py
telectron/errors/exceptions/service_unavailable_503.py
telectron/errors/exceptions/unauthorized_401.py
telectron/handlers/__init__.py
